chatwithkafka/__init__.py
chatwithkafka/app.py
chatwithkafka/app.tcss
chatwithkafka/cli.py
chatwithkafka/key.py
chatwithkafka-0.1.2.dist-info/LICENSE
chatwithkafka-0.1.2.dist-info/METADATA
chatwithkafka-0.1.2.dist-info/WHEEL
chatwithkafka-0.1.2.dist-info/entry_points.txt
chatwithkafka-0.1.2.dist-info/top_level.txt
chatwithkafka-0.1.2.dist-info/RECORD
