Metadata-Version: 2.1
Name: chatwithkafka
Version: 0.1.2
Summary: A Kafka Chat application as a TUI
Home-page: https://github.com/swedwise/Swedwise.ChatWithKafka
Author: Henrik Blidh
Author-email: henrik.blidh@swedwise.se
License: MIT
Keywords: kafka,chat,tui
Classifier: Programming Language :: Python :: 3
Requires-Python: >=3.8
License-File: LICENSE
Requires-Dist: confluent-kafka
Requires-Dist: textual
Requires-Dist: tzlocal
Requires-Dist: cryptography
